{
    "name": "Lychee Tree 🌼",
    "category": "patchouli:trees",
    "icon": "pamhc2trees:lychee_sapling",
    "sortnum": -1,
    "pages": [
        {
            "type": "patchouli:text",
            "text": "$(l)Stats$()$(li)🌼 §2Spring§r $(li)Price: :coin: 256$(li)Size: 1x1$(li)Grows:$(l:tree_crops/lychee)8x Lychee$(/l)$(br2)$(l)Notes$()$(li)Saplings bought from Market."
        },
        {
            "type": "patchouli:multiblock",
            "name ": "Lychee Tree",
            "enable_visualize": false,
            "multiblock": {
                "mapping": {
                    "0": "minecraft:jungle_leaves",
                    "L": "minecraft:jungle_leaves",
                    "W": "minecraft:jungle_log[axis=y]",
                    "F": "pamhc2trees:pamlychee[age=7]"
                },
                "pattern": [
                    [
                        "     ",
                        "     ",
                        "  0  ",
                        "     ",
                        "     "
                    ],
                    [
                        "     ",
                        "     ",
                        "  L  ",
                        "     ",
                        "     "
                    ],
                    [
                        "     ",
                        " LLL ",
                        " LWL ",
                        " LLL ",
                        "     "
                    ],
                    [
                        "     ",
                        " LLL ",
                        " LWL ",
                        " LLL ",
                        "     "
                    ],
                    [
                        "LLLLL",
                        "LLLLL",
                        "LLWLL",
                        "LLLLL",
                        "LLLLL"
                    ],
                    [
                        "     ",
                        " FFF ",
                        " FWF ",
                        " FFF ",
                        "     "
                    ],
                    [
                        "     ",
                        "     ",
                        "  W  ",
                        "     ",
                        "     "
                    ],
                    [
                        "     ",
                        "     ",
                        "  W  ",
                        "     ",
                        "     "
                    ]
                ]
            }
        }
    ]
}