{
  "content": {
    "obj_catch_anything": {
      "type": "criteria",
      "rarity": "RARE",
      "name": "Fish up anything",
      "content": "minecraft:fishing_rod_hooked",
      "conditions": {
        "type_specific": {
          "fishing_hook": {
            "in_open_water": true
          }
        }
      },
      "amount": {
        "min": 2,
        "max": 10
      },
      "unitWorth": 64,
      "timeMult": 3,
      "weightMult": 0.6
    },
    "farmer_obj_chop_on_cutting_board": {
      "type": "criteria",
      "rarity": "COMMON",
      "name": "Chop things on a farmer's delight cutting board",
      "content": "farmersdelight:use_cutting_board",
      "conditions": {},
      "amount": {
        "min": 1,
        "max": 16
      },
      "unitWorth": 8,
      "timeMult": 2,
      "weightMult": 0.5
    }
  }
}
