{
  "name": "Zucchini 🔥",
  "category": "patchouli:crops",
  "icon": "veggiesdelight:zucchini",
  "pages": [
    {
      "type": "patchouli:text",
      "text": "$(l)Stats$()$(li):coin: 72$(li)🔥 §6Summer§r $(li)Seed Price: Not sold$(li)Yield: 1-2$(li)Grow time: 7 days"
    },
    {
      "type": "patchouli:multiblock",
      "name ": "Zucchini Crop",
      "enable_visualize": false,
      "multiblock": {
        "pattern": [["0"], ["F"]],
        "mapping": {
          "0": "veggiesdelight:zucchini_crop[age=7]",
          "F": "minecraft:farmland[moisture=7]"
        }
      }
    }
  ]
}
